wwpdb/utils/cc_dict_util/__init__.py
wwpdb/utils/cc_dict_util/persist/PdbxChemCompCategoryDefinitions.py
wwpdb/utils/cc_dict_util/persist/PdbxChemCompConstants.py
wwpdb/utils/cc_dict_util/persist/PdbxChemCompDictIndex.py
wwpdb/utils/cc_dict_util/persist/PdbxChemCompDictUtil.py
wwpdb/utils/cc_dict_util/persist/PdbxChemCompPersist.py
wwpdb/utils/cc_dict_util/persist/__init__.py
wwpdb/utils/cc_dict_util/timeout/TimeoutMultiProc.py
wwpdb/utils/cc_dict_util/timeout/__init__.py
wwpdb/utils/cc_dict_util/timeout/py.typed
wwpdb_utils_cc_dict_util-0.5.2.dist-info/METADATA
wwpdb_utils_cc_dict_util-0.5.2.dist-info/WHEEL
wwpdb_utils_cc_dict_util-0.5.2.dist-info/RECORD
