Metadata-Version: 2.4
Name: wwpdb.utils.cc-dict-util
Version: 0.5.2
Summary: wwPDB CCD Persistence
Project-URL: Homepage, https://github.com/rcsb/py-wwpdb_utils_cc_dict_util
Author-email: Ezra Peisach <ezra.peisach@rcsb.org>
License-Expression: Apache-2.0
Classifier: Development Status :: 3 - Alpha
Classifier: Intended Audience :: Developers
Classifier: License :: OSI Approved :: Apache Software License
Classifier: Natural Language :: English
Classifier: Programming Language :: Python
Classifier: Programming Language :: Python :: 3
Classifier: Programming Language :: Python :: 3.6
Classifier: Programming Language :: Python :: 3.7
Requires-Python: >=3.6
Requires-Dist: mmcif-utils>=0.17
Requires-Dist: typing-extensions; python_version <= '3.9'
